fiddle/__init__.py
fiddle/arg_factory.py
fiddle/building.py
fiddle/config.py
fiddle/config_test.py
fiddle/daglish.py
fiddle/diffing.py
fiddle/graphviz.py
fiddle/history.py
fiddle/printing.py
fiddle/selectors.py
fiddle/signatures.py
fiddle/tag_type.py
fiddle/tagging.py
fiddle/validation.py
fiddle/version.py
fiddle/_src/__init__.py
fiddle/_src/arg_factory.py
fiddle/_src/arg_factory_test.py
fiddle/_src/building.py
fiddle/_src/building_test.py
fiddle/_src/casting.py
fiddle/_src/config.py
fiddle/_src/config_test.py
fiddle/_src/copying.py
fiddle/_src/copying_test.py
fiddle/_src/daglish.py
fiddle/_src/daglish_extensions.py
fiddle/_src/daglish_extensions_test.py
fiddle/_src/daglish_test.py
fiddle/_src/diffing.py
fiddle/_src/diffing_test.py
fiddle/_src/graphviz.py
fiddle/_src/graphviz_custom_object.py
fiddle/_src/history.py
fiddle/_src/history_test.py
fiddle/_src/materialize.py
fiddle/_src/materialize_test.py
fiddle/_src/module_reflection.py
fiddle/_src/module_reflection_test.py
fiddle/_src/module_reflection_test_module.py
fiddle/_src/mutate_buildable.py
fiddle/_src/mutate_buildable_test.py
fiddle/_src/partial.py
fiddle/_src/partial_test.py
fiddle/_src/printing.py
fiddle/_src/printing_test.py
fiddle/_src/reraised_exception.py
fiddle/_src/reraised_exception_test.py
fiddle/_src/selectors.py
fiddle/_src/selectors_test.py
fiddle/_src/signatures.py
fiddle/_src/signatures_test.py
fiddle/_src/signatures_test_helper.py
fiddle/_src/special_overrides.py
fiddle/_src/tag_type.py
fiddle/_src/tagging.py
fiddle/_src/tagging_test.py
fiddle/_src/tagging_test_module.py
fiddle/_src/absl_flags/__init__.py
fiddle/_src/absl_flags/flags.py
fiddle/_src/absl_flags/legacy_flags.py
fiddle/_src/absl_flags/sample_module_for_flags_test.py
fiddle/_src/absl_flags/sample_test_binary.py
fiddle/_src/absl_flags/utils.py
fiddle/_src/codegen/__init__.py
fiddle/_src/codegen/codegen_diff.py
fiddle/_src/codegen/formatting_utilities.py
fiddle/_src/codegen/import_manager.py
fiddle/_src/codegen/import_manager_test.py
fiddle-0.3.0.dist-info/LICENSE
fiddle-0.3.0.dist-info/METADATA
fiddle-0.3.0.dist-info/WHEEL
fiddle-0.3.0.dist-info/top_level.txt
fiddle-0.3.0.dist-info/RECORD
